<?xml version="1.0" encoding="UTF-8"?>
<PointFinderArguments>
  <OutputDirectory>C:\temp\out</OutputDirectory>
  <OutputFilenamePrefix>Points</OutputFilenamePrefix>
  <MinimumThreshold>1000</MinimumThreshold>
  <MaximumThreshold>2000</MaximumThreshold>
  <SelectionStrategy>EdgesWithBulbsExcluded</SelectionStrategy>
  <!--The following are only required with the strategy includes edge detection-->
  <InputDirectory>C:\temp\in</InputDirectory>
  <InputEdgeFilename>Edge.edge</InputEdgeFilename>
</PointFinderArguments>